ufactory_sila2_server/__init__.py
ufactory_sila2_server/__main__.py
ufactory_sila2_server/py.typed
ufactory_sila2_server/server.py
ufactory_sila2_server/test_in_out.py
ufactory_sila2_server/feature_implementations/__init__.py
ufactory_sila2_server/feature_implementations/gripper.py
ufactory_sila2_server/feature_implementations/gripper_base.py
ufactory_sila2_server/feature_implementations/gripper_fb360.py
ufactory_sila2_server/feature_implementations/tempCodeRunnerFile.py
ufactory_sila2_server/feature_implementations/test_arm.py
ufactory_sila2_server/feature_implementations/test_client.py
ufactory_sila2_server/feature_implementations/ufcontroller_impl.py
ufactory_sila2_server/generated/__init__.py
ufactory_sila2_server/generated/client.py
ufactory_sila2_server/generated/ufcontroller/UFController.proto
ufactory_sila2_server/generated/ufcontroller/UFController.sila.xml
ufactory_sila2_server/generated/ufcontroller/__init__.py
ufactory_sila2_server/generated/ufcontroller/ufcontroller_base.py
ufactory_sila2_server/generated/ufcontroller/ufcontroller_client.py
ufactory_sila2_server/generated/ufcontroller/ufcontroller_errors.py
ufactory_sila2_server/generated/ufcontroller/ufcontroller_feature.py
ufactory_sila2_server/generated/ufcontroller/ufcontroller_types.py
ufactory_sila2_server-0.1.5.dist-info/METADATA
ufactory_sila2_server-0.1.5.dist-info/WHEEL
ufactory_sila2_server-0.1.5.dist-info/top_level.txt
ufactory_sila2_server-0.1.5.dist-info/RECORD
