Metadata-Version: 2.1
Name: ufactory_sila2_server
Version: 0.1.5
Requires-Python: >=3.8
Requires-Dist: sila2
Requires-Dist: typer
Requires-Dist: xArm-Python-SDK
